{
  "formatVersion": 1,
  "database": {
    "version": 1,
    "identityHash": "ba17304f0f21bb1df4d064e10977055b",
    "entities": [
      {
        "tableName": "country",
        "createSql": "CREATE TABLE IF NOT EXISTS `${TABLE_NAME}` (`cid` INTEGER PRIMARY KEY AUTOINCREMENT NOT NULL, `country_name` TEXT, `country_code` TEXT)",
        "fields": [
          {
            "fieldPath": "cid",
            "columnName": "cid",
            "affinity": "INTEGER",
            "notNull": true
          },
          {
            "fieldPath": "countryName",
            "columnName": "country_name",
            "affinity": "TEXT",
            "notNull": false
          },
          {
            "fieldPath": "countryCode",
            "columnName": "country_code",
            "affinity": "TEXT",
            "notNull": false
          }
        ],
        "primaryKey": {
          "columnNames": [
            "cid"
          ],
          "autoGenerate": true
        },
        "indices": [],
        "foreignKeys": []
      }
    ],
    "setupQueries": [
      "CREATE TABLE IF NOT EXISTS room_master_table (id INTEGER PRIMARY KEY,identity_hash TEXT)",
      "INSERT OR REPLACE INTO room_master_table (id,identity_hash) VALUES(42, \"ba17304f0f21bb1df4d064e10977055b\")"
    ]
  }
}